pear_software_devtoolkit/__init__.py
pear_software_devtoolkit/cli.py
pear_software_devtoolkit/commands/__init__.py
pear_software_devtoolkit/commands/base64.py
pear_software_devtoolkit/commands/cheats.py
pear_software_devtoolkit/commands/colorize.py
pear_software_devtoolkit/commands/envgen.py
pear_software_devtoolkit/commands/file_stats.py
pear_software_devtoolkit/commands/gen_password.py
pear_software_devtoolkit/commands/git_ignore.py
pear_software_devtoolkit/commands/hash.py
pear_software_devtoolkit/commands/ipinfo.py
pear_software_devtoolkit/commands/jsonfmt.py
pear_software_devtoolkit/commands/lorem.py
pear_software_devtoolkit/commands/mkproject.py
pear_software_devtoolkit/commands/port_check.py
pear_software_devtoolkit/commands/regex_tester.py
pear_software_devtoolkit/commands/slugify.py
pear_software_devtoolkit/commands/timer.py
pear_software_devtoolkit/commands/timestamp.py
pear_software_devtoolkit/commands/unit_convert.py
pear_software_devtoolkit/commands/url_decode.py
pear_software_devtoolkit/commands/url_encode.py
pear_software_devtoolkit/commands/uuid.py
pear_software_devtoolkit/commands/whoami.py
pear_software_devtoolkit/utils.py
pear_software_devtoolkit-0.1.0.dist-info/entry_points.txt
pear_software_devtoolkit-0.1.0.dist-info/METADATA
pear_software_devtoolkit-0.1.0.dist-info/WHEEL
pear_software_devtoolkit-0.1.0.dist-info/RECORD
